razan_module/__init__.py
razan_module/razan_module.py
dataprepkitRazan-0.1.dist-info/LICENSE
dataprepkitRazan-0.1.dist-info/METADATA
dataprepkitRazan-0.1.dist-info/WHEEL
dataprepkitRazan-0.1.dist-info/top_level.txt
dataprepkitRazan-0.1.dist-info/RECORD
