Metadata-Version: 2.1
Name: dataprepkitRazan
Version: 0.1
Summary: Package for data preparation
Home-page: https://github.com/razan2024/prekitRazan
Author: razan2024
Author-email: razansharaf5@gmail.com
License: MIT
Keywords: data,preparation,tools
Classifier: License :: OSI Approved :: MIT License
Classifier: Programming Language :: Python :: 3
Classifier: Operating System :: OS Independent
License-File: LICENSE
